MANIFEST.in
README.txt
setup.py
collective/__init__.py
collective.jquerytablehover.egg-info/PKG-INFO
collective.jquerytablehover.egg-info/SOURCES.txt
collective.jquerytablehover.egg-info/dependency_links.txt
collective.jquerytablehover.egg-info/entry_points.txt
collective.jquerytablehover.egg-info/namespace_packages.txt
collective.jquerytablehover.egg-info/not-zip-safe
collective.jquerytablehover.egg-info/requires.txt
collective.jquerytablehover.egg-info/top_level.txt
collective/jquerytablehover/__init__.py
collective/jquerytablehover/configure.zcml
collective/jquerytablehover/jquery.tablehover.js
collective/jquerytablehover/profiles/default/jsregistry.xml
collective/jquerytablehover/profiles/default/metadata.xml